<?xml version="1.0" encoding="UTF-8"?>
<record_update table="sp_instance">
    <sp_instance action="INSERT_OR_UPDATE">
        <active>true</active>
        <class_name/>
        <color>default</color>
        <css/>
        <glyph/>
        <id/>
        <order>0</order>
        <short_description/>
        <size>md</size>
        <sp_column display_value="1">8f6f5f684f62cb00f78e74828110c76c</sp_column>
        <sp_widget display_value="EMP Personnel Assets Form">cd2fa369dbd00300e5c755d0cf96197b</sp_widget>
        <sys_class_name>sp_instance</sys_class_name>
        <sys_created_by>jade.garcia</sys_created_by>
        <sys_created_on>2017-11-06 19:18:39</sys_created_on>
        <sys_customer_update>true</sys_customer_update>
        <sys_id>016937454fd24700ec6c3cb28110c70f</sys_id>
        <sys_mod_count>2</sys_mod_count>
        <sys_name/>
        <sys_package display_value="Employee Management Portal" source="x_134426_emp">06136fe0dbd04300e5c755d0cf961930</sys_package>
        <sys_policy/>
        <sys_replace_on_upgrade>false</sys_replace_on_upgrade>
        <sys_scope display_value="Employee Management Portal">06136fe0dbd04300e5c755d0cf961930</sys_scope>
        <sys_update_name>sp_instance_016937454fd24700ec6c3cb28110c70f</sys_update_name>
        <sys_updated_by>jade.garcia</sys_updated_by>
        <sys_updated_on>2017-11-17 14:24:05</sys_updated_on>
        <title/>
        <url/>
        <widget_parameters/>
    </sp_instance>
</record_update>
